fread/get_input.py
fread-1.0.dist-info/LICENSE
fread-1.0.dist-info/METADATA
fread-1.0.dist-info/WHEEL
fread-1.0.dist-info/top_level.txt
fread-1.0.dist-info/RECORD
