Metadata-Version: 2.1
Name: fread
Version: 1.0
Summary: A python package to change from Interaction console based code to file based code
Home-page: UNKNOWN
Author: Venkata Sai Srinivas Paila
Author-email: pailasaisrinivas7668@gmail.com
License: MIT
Platform: UNKNOWN
Classifier: Intended Audience :: Education
Classifier: License :: OSI Approved :: MIT License
Classifier: Programming Language :: Python :: 3
Classifier: Programming Language :: Python :: 3.4
Classifier: Programming Language :: Python :: 3.5
Classifier: Programming Language :: Python :: 3.6
